revChatGPTAuth/__init__.py
revChatGPTAuth/chatgpt_access_token_parser.py
revChatGPTAuth/openai_cookie_parser.py
revChatGPTAuth/py.typed
revChatGPTAuth/supported_browser.py
revChatGPTAuth/test/__init__.py
revChatGPTAuth/test/test_chatgpt_access_token_parser.py
revChatGPTAuth/test/test_openai_cookie_parser.py
revChatGPTAuth/utils.py
revchatgptauth-2023.4.16.dist-info/METADATA
revchatgptauth-2023.4.16.dist-info/WHEEL
revchatgptauth-2023.4.16.dist-info/RECORD
