Metadata-Version: 2.1
Name: revchatgptauth
Version: 2023.4.16
Summary: 
Requires-Python: >=3.9,<4.0
Classifier: Programming Language :: Python :: 3
Classifier: Programming Language :: Python :: 3.9
Classifier: Programming Language :: Python :: 3.10
Classifier: Programming Language :: Python :: 3.11
Requires-Dist: browser-cookie3 (>=0.17.1,<0.18.0)
Requires-Dist: httpx (>=0.24.0,<0.25.0)
Requires-Dist: poetry (>=1.4.2,<2.0.0)
